libusb_package/_version.py
libusb_package/py.typed
libusb_package/libusb-1.0.so
libusb_package/__init__.py
libusb_package/__pyinstaller/hook-libusb_package.py
libusb_package/__pyinstaller/__init__.py
libusb_pkg-1.0.26.3.dist-info/WHEEL
libusb_pkg-1.0.26.3.dist-info/RECORD
libusb_pkg-1.0.26.3.dist-info/top_level.txt
libusb_pkg-1.0.26.3.dist-info/entry_points.txt
libusb_pkg-1.0.26.3.dist-info/METADATA
libusb_pkg-1.0.26.3.dist-info/licenses/LICENSE
