Metadata-Version: 2.4
Name: libusb-pkg
Version: 1.0.26.3
Summary: Package containing libusb so it can be installed via Python package managers
Home-page: https://github.com/pyocd/libusb-package
Author: Chris Reed
Author-email: flit@me.com
License: Apache 2.0
Project-URL: Bug Tracker, https://github.com/pyocd/libusb-package/issues
Project-URL: Discussions, https://github.com/pyocd/libusb-package/discussions
Project-URL: Changelog, https://github.com/pyocd/libusb-package/releases
Classifier: Development Status :: 4 - Beta
Classifier: Intended Audience :: Developers
Classifier: License :: OSI Approved :: Apache Software License
Classifier: Operating System :: MacOS
Classifier: Operating System :: Microsoft :: Windows
Classifier: Operating System :: POSIX
Classifier: Operating System :: Unix
Classifier: Programming Language :: Python
Classifier: Programming Language :: Python :: 3.7
Classifier: Programming Language :: Python :: 3.8
Classifier: Programming Language :: Python :: 3.9
Classifier: Programming Language :: Python :: 3.10
Classifier: Programming Language :: Python :: 3.11
Classifier: Programming Language :: Python :: 3.12
Classifier: Programming Language :: Python :: 3.13
Classifier: Topic :: System :: Hardware :: Universal Serial Bus (USB)
Classifier: Typing :: Typed
Requires-Python: >=3.9
License-File: LICENSE
Requires-Dist: importlib_resources
Dynamic: license-file
